Metadata-Version: 2.1
Name: base-folder-atstaeff
Version: 0.0.1
Summary: Streaming video data via networks
Home-page: UNKNOWN
Author: Stefan Poss)
Author-email: sp@stefanposs.de
License: UNKNOWN
Keywords: python
Platform: UNKNOWN
Classifier: Development Status :: 1 - Planning
Classifier: Intended Audience :: Developers
Classifier: Programming Language :: Python :: 3
Classifier: Operating System :: Unix
Classifier: Operating System :: MacOS :: MacOS X
Classifier: Operating System :: Microsoft :: Windows
License-File: LICENSE
